lc3_ensemble_test-0.1.12.dist-info/METADATA
lc3_ensemble_test-0.1.12.dist-info/WHEEL
lc3_ensemble_test-0.1.12.dist-info/licenses/LICENSE
ensemble_test/autograder/__init__.py
ensemble_test/core/__init__.py
ensemble_test/ensemble_test.pyi
ensemble_test/__init__.py
ensemble_test/ensemble_test.cp311-win_amd64.pyd
lc3_ensemble_test-0.1.12.dist-info/RECORD
