Metadata-Version: 2.4
Name: lc3-ensemble-test
Version: 0.1.12
Classifier: Programming Language :: Rust
Classifier: Programming Language :: Python :: Implementation :: CPython
Classifier: Programming Language :: Python :: Implementation :: PyPy
Requires-Dist: parameterized==0.9.0 ; extra == 'std'
Requires-Dist: pytest==8.2.2 ; extra == 'std'
Requires-Dist: pytest-html==4.1.1 ; extra == 'std'
Provides-Extra: std
License-File: LICENSE
Summary: Python backend and autograder library for LC-3 assembly
Author: Henry Bui
Requires-Python: >=3.8
Project-URL: Repository, https://github.com/endorpersand/lc3-ensemble-test
